ratsoup/__init__.py
ratsoup/rats.py
ratsoup/test_rats.py
ratsoup-0.2.dist-info/DESCRIPTION.rst
ratsoup-0.2.dist-info/METADATA
ratsoup-0.2.dist-info/RECORD
ratsoup-0.2.dist-info/WHEEL
ratsoup-0.2.dist-info/entry_points.txt
ratsoup-0.2.dist-info/metadata.json
ratsoup-0.2.dist-info/top_level.txt
