Metadata-Version: 2.0
Name: ratsoup
Version: 0.2
Summary: Make soup for the rats
Home-page: https://github.com/gabrielx52/ratsoup.git
Author: Paul Fablanod
Author-email: p.fablanod@gmail.com
License: UNKNOWN
Download-URL: https://github.com/gabrielx52/ratsoup/archive/0.2.tar.gz
Keywords: rat,rats,soup
Platform: UNKNOWN
